bumbov/__init__.py
bumbov/api.py
bumbov/middleware.py
bumbov/orm.py
bumbov/response.py
tests/__init__.py
tests/conftest.py
tests/test_fram.py
tests/test_orm.py
bumbov-0.0.5.dist-info/METADATA
bumbov-0.0.5.dist-info/WHEEL
bumbov-0.0.5.dist-info/top_level.txt
bumbov-0.0.5.dist-info/RECORD
