Metadata-Version: 2.1
Name: bumbov
Version: 0.0.5
Summary: Bumbov Python Web Framework built for learning purposes.
Home-page: UNKNOWN
Author: Mohamed Sakr
Author-email: mohamed1.sakr1996@gmail.com
License: MIT
Platform: UNKNOWN
Classifier: Programming Language :: Python :: 3.6
Requires-Python: >=3.6.0
Requires-Dist: Jinja2 (==3.1.2)
Requires-Dist: WebOb (==1.8.7)
Requires-Dist: parse (==1.12.1)
Requires-Dist: requests-wsgi-adapter (==0.4.1)
Requires-Dist: requests (==2.22.0)
Requires-Dist: whitenoise (==6.2.0)
